starparser/__init__.py
starparser/__main__.py
starparser/argparser.py
starparser/columnplay.py
starparser/decisiontree.py
starparser/fileparser.py
starparser/particleplay.py
starparser/plots.py
starparser/specialparticles.py
starparser/splits.py
starparser-1.39.dist-info/LICENSE.txt
starparser-1.39.dist-info/METADATA
starparser-1.39.dist-info/WHEEL
starparser-1.39.dist-info/entry_points.txt
starparser-1.39.dist-info/top_level.txt
starparser-1.39.dist-info/RECORD
