Metadata-Version: 2.1
Name: starparser
Version: 1.39
Summary: Manipulate and mine Relion star files.
Home-page: http://pypi.python.org/pypi/starparser/
Author: Sami Chaaban
Author-email: chaaban@mrc-lmb.cam.ac.uk
Requires-Python: >=3.6
License-File: LICENSE.txt
Requires-Dist: numpy
Requires-Dist: pandas
Requires-Dist: matplotlib
Requires-Dist: scipy
